odoo/addons/shipment_advice_reception_planner/README.rst
odoo/addons/shipment_advice_reception_planner/__init__.py
odoo/addons/shipment_advice_reception_planner/__manifest__.py
odoo/addons/shipment_advice_reception_planner/i18n/shipment_advice_reception_planner.pot
odoo/addons/shipment_advice_reception_planner/models/__init__.py
odoo/addons/shipment_advice_reception_planner/models/shipment_advice.py
odoo/addons/shipment_advice_reception_planner/models/stock_move.py
odoo/addons/shipment_advice_reception_planner/readme/CONTRIBUTORS.rst
odoo/addons/shipment_advice_reception_planner/readme/DESCRIPTION.rst
odoo/addons/shipment_advice_reception_planner/security/ir.model.access.csv
odoo/addons/shipment_advice_reception_planner/static/description/icon.png
odoo/addons/shipment_advice_reception_planner/static/description/index.html
odoo/addons/shipment_advice_reception_planner/tests/__init__.py
odoo/addons/shipment_advice_reception_planner/tests/test_shipment_advice_reception_planner.py
odoo/addons/shipment_advice_reception_planner/views/shipment_advice.xml
odoo/addons/shipment_advice_reception_planner/views/stock_move.xml
odoo/addons/shipment_advice_reception_planner/wizards/__init__.py
odoo/addons/shipment_advice_reception_planner/wizards/plan_reception_shipment.py
odoo/addons/shipment_advice_reception_planner/wizards/plan_reception_shipment.xml
odoo/addons/shipment_advice_reception_planner/wizards/stock_move_split.py
odoo/addons/shipment_advice_reception_planner/wizards/unplan_shipment.py
odoo14_addon_shipment_advice_reception_planner-14.0.0.2.0.dist-info/METADATA
odoo14_addon_shipment_advice_reception_planner-14.0.0.2.0.dist-info/WHEEL
odoo14_addon_shipment_advice_reception_planner-14.0.0.2.0.dist-info/top_level.txt
odoo14_addon_shipment_advice_reception_planner-14.0.0.2.0.dist-info/RECORD
