Metadata-Version: 2.1
Name: odoo14-addon-shipment_advice_reception_planner
Version: 14.0.0.2.0
Summary: Plan your reception into shipment advices.
Home-page: https://github.com/OCA/stock-logistics-transport
Author: Camptocamp, Odoo Community Association (OCA)
Author-email: support@odoo-community.org
License: AGPL-3
Classifier: Programming Language :: Python
Classifier: Framework :: Odoo
Classifier: Framework :: Odoo :: 14.0
Classifier: License :: OSI Approved :: GNU Affero General Public License v3
Requires-Python: >=3.6
Requires-Dist: odoo14-addon-shipment-advice
Requires-Dist: odoo <14.1dev,>=14.0a
